sacredboard/__init__.py
sacredboard/bootstrap.py
sacredboard/app/__init__.py
sacredboard/app/sacredboard.py
sacredboard/app/business/__init__.py
sacredboard/app/business/runfacade.py
sacredboard/app/config/__init__.py
sacredboard/app/config/jinja_filters.py
sacredboard/app/data/__init__.py
sacredboard/app/data/datastorage.py
sacredboard/app/data/errors.py
sacredboard/app/data/metricsdao.py
sacredboard/app/data/rundao.py
sacredboard/app/data/filestorage/__init__.py
sacredboard/app/data/filestorage/filestorage.py
sacredboard/app/data/filestorage/filestorecursor.py
sacredboard/app/data/filestorage/rundao.py
sacredboard/app/data/pymongo/__init__.py
sacredboard/app/data/pymongo/genericdao.py
sacredboard/app/data/pymongo/metricsdao.py
sacredboard/app/data/pymongo/mongocursor.py
sacredboard/app/data/pymongo/mongodb.py
sacredboard/app/data/pymongo/rundao.py
sacredboard/app/process/__init__.py
sacredboard/app/process/process.py
sacredboard/app/process/tensorboard.py
sacredboard/app/webapi/__init__.py
sacredboard/app/webapi/metrics.py
sacredboard/app/webapi/proxy.py
sacredboard/app/webapi/routes.py
sacredboard/app/webapi/runs.py
sacredboard/app/webapi/wsgi_server.py
sacredboard/static/css/runs.css
sacredboard/static/scripts/command.js
sacredboard/static/scripts/enquotedStringOrNumberValidator.js
sacredboard/static/scripts/escapeHtml.js
sacredboard/static/scripts/main.js
sacredboard/static/scripts/metricsPlot/component.js
sacredboard/static/scripts/metricsPlot/template.html
sacredboard/static/scripts/metricsPlot/test.html
sacredboard/static/scripts/plot/Series.js
sacredboard/static/scripts/plot/component.js
sacredboard/static/scripts/plot/plot.js
sacredboard/static/scripts/plot/template.html
sacredboard/static/scripts/plot/test.html
sacredboard/static/scripts/plot/plotlyplot/PlotlyPlot.js
sacredboard/static/scripts/plot/plotlyplot/convertDataPoints.js
sacredboard/static/scripts/plot/plotlyplot/formatDate.js
sacredboard-0.4.2.dist-info/METADATA
sacredboard-0.4.2.dist-info/RECORD
sacredboard-0.4.2.dist-info/WHEEL
sacredboard-0.4.2.dist-info/entry_points.txt
sacredboard-0.4.2.dist-info/top_level.txt
